info_ratio/__init__.py
info_ratio/common/__init__.py
info_ratio/common/helper_functions.py
info_ratio/common/input_output.py
info_ratio/common/logging.py
info_ratio/core.py
info_ratio-0.1.9.dist-info/LICENSE
info_ratio-0.1.9.dist-info/METADATA
info_ratio-0.1.9.dist-info/WHEEL
info_ratio-0.1.9.dist-info/RECORD
